my_little_helper/__init__.py
my_little_helper/data.py
my_little_helper-0.0.1.dist-info/METADATA
my_little_helper-0.0.1.dist-info/WHEEL
my_little_helper-0.0.1.dist-info/top_level.txt
my_little_helper-0.0.1.dist-info/RECORD
